{
  "schema_version": 1,
  "quilt_loader": {
    "group": "io.github.glyphmc",
    "id": "glyph",
    "version": "${version}",
    "metadata": {
      "name": "Glyph",
      "description": "[Redacted]",
      "contributors": {
        "GlyphMC": "Owner",
        "IMS212": "Contributor",
        "NoComment1105": "Contributor",
        "Maximum": "Contributor",
        "CarbonGhost": "Contributor",
        "chalkyjeans": "Contributor"
      },
      "contact": {
        "homepage": "https://github.com/GlyphMC/client",
        "issues": "https://github.com/GlyphMC/client/issues",
        "sources": "https://github.com/GlyphMC/client/"
      },
      "license": "LGPL-3.0",
      "icon": "assets/glyph/icon.png"
    },
    "intermediate_mappings": "net.fabricmc:intermediary",
    "entrypoints": {
      "client_init": "io.github.glyphmc.glyph.GlyphClient",
      "modmenu": [
        "io.github.glyphmc.glyph.compat.modmenu.ModMenuIntegration"
      ]
    },
    "depends": [
      "quilt_loader",
      "quilted_fabric_api",
      "fabric-language-kotlin"
    ]
  },
  "mixin": [
    "glyph.mixins.json"
  ]
}
